<?xml version="1.0" encoding="UTF-8"?>
<model-companion xmlns="http://www.fico.com/xpress/optimization-modeler/model-companion" version="3.0">

    <client>
        <view-group title="Main">
            <vdl-view title="Welcome" path="welcome.vdl" requires-scenarios-loaded="false"/>
            <vdl-view title="Example One" path="datagrid.vdl"/>
        </view-group>
        <view-group title="vdlx-datagrid Features">
            <vdl-view title="Basic usage" path="vdl-lang/table/table.vdl"/>
            <vdl-view title="Editable tables" path="vdl-lang/table/table-editable.vdl"/>
            <vdl-view title="Editable tables - Select inputs" path="vdl-lang/table/table-editable-select.vdl"/>
            <vdl-view title="Multi-scenario" path="vdl-lang/table/table-multi-scenario.vdl"/>
            <vdl-view title="Conditionals" path="vdl-lang/table/table-conditionals.vdl"/>
            <vdl-view title="Index filtering" path="vdl-lang/table/table-index-filtering.vdl"/>
            <vdl-view title="Row filtering" path="vdl-lang/table/table-row-filtering.vdl"/>
            <vdl-view title="Error handling" path="vdl-lang/table/table-errors.vdl"/>
            <vdl-view title="Validation" path="vdl-lang/table/table-validation.vdl"/>
        </view-group>

        <view-group title="Big Data">
            <vdl-view title="Big Data Table 1" path="big-data/datagrid-bd1.vdl"/>
            <vdl-view title="Big Data Table 2" path="big-data/datagrid-bd2.vdl"/>
            <vdl-view title="Big Data Table 3" path="big-data/datagrid-bd3.vdl"/>
            <vdl-view title="Big Data Table 4" path="big-data/datagrid-bd4.vdl"/>
            <vdl-view title="Big Data Table 5" path="big-data/datagrid-bd5.vdl"/>
        </view-group>

        <view-group title="vdlx-datagrid Features">
            <vdl-view title="VXDG - Basic Usage" path="datagrid/datagrid.vdl"/>
        </view-group>

        <client-resources-local-path>/Users/e48378/Documents/support/curtisfranks/table-performance/insight/client_resources</client-resources-local-path>

    </client>
</model-companion>